Metadata-Version: 1.1
Name: numfu
Version: 0.0.1
Summary: Master the numpy arts
Home-page: UNKNOWN
Author: kevin mcguigan
Author-email: UNKNOWN
License: MIT
Download-URL: https://github.com/kevinkmcguigan/numfu/archive/refs/tags/0.0.1.tar.gz
Keywords: numpy,snippits
Platform: UNKNOWN
Classifier: Development Status :: 1 - Planning
